sclblpy/__init__.py
sclblpy/__main__.py
sclblpy/_appdirs.py
sclblpy/_globals.py
sclblpy/auth.py
sclblpy/compute.py
sclblpy/device.py
sclblpy/errors.py
sclblpy/glob.json
sclblpy/main.py
sclblpy/version.py
sclblpy-0.1.10.dist-info/LICENSE
sclblpy-0.1.10.dist-info/METADATA
sclblpy-0.1.10.dist-info/WHEEL
sclblpy-0.1.10.dist-info/top_level.txt
sclblpy-0.1.10.dist-info/RECORD
