Metadata-Version: 2.1
Name: sclblpy
Version: 0.1.10
Summary: Python package for interacting with our API.
Home-page: https://github.com/scailable/sclblpy/
Author: Maurits Kaptein
Author-email: maurits.kaptein@scailable.net
Classifier: Programming Language :: Python :: 3
Classifier: License :: OSI Approved :: MIT License
Classifier: Operating System :: OS Independent
Requires-Python: >=3.7
License-File: LICENSE
Requires-Dist: requests
Requires-Dist: pyjwt
